pytest_logging_strict/__init__.py
pytest_logging_strict/__init__.pyi
pytest_logging_strict/_version.py
pytest_logging_strict/_version.pyi
pytest_logging_strict/plugin_shared.py
pytest_logging_strict/plugin_shared.pyi
pytest_logging_strict/plugin_v0.py
pytest_logging_strict/plugin_v0.pyi
pytest_logging_strict/plugin_v1.py
pytest_logging_strict/plugin_v1.pyi
pytest_logging_strict/plugin_wireframe.py
pytest_logging_strict/plugin_wireframe.pyi
pytest_logging_strict/py.typed
pytest_logging_strict/util.py
pytest_logging_strict/util.pyi
pytest_logging_strict/util_xdist.py
pytest_logging_strict/util_xdist.pyi
pytest_logging_strict-0.2.3.dist-info/licenses/LICENSE
pytest_logging_strict-0.2.3.dist-info/licenses/NOTICE.txt
pytest_logging_strict-0.2.3.dist-info/METADATA
pytest_logging_strict-0.2.3.dist-info/WHEEL
pytest_logging_strict-0.2.3.dist-info/entry_points.txt
pytest_logging_strict-0.2.3.dist-info/top_level.txt
pytest_logging_strict-0.2.3.dist-info/RECORD
