Metadata-Version: 2.4
Name: pytest-logging-strict
Version: 0.2.3
Summary: pytest fixture logging configured from packaged YAML
Author-email: Dave Faulkmore <faulkmore@protonmail.com>
Maintainer-email: Dave Faulkmore <faulkmore@protonmail.com>
License-Expression: AGPL-3.0-or-later
Project-URL: Changes, https://raw.githubusercontent.com/msftcangoblowm/pytest-logging-strict/master/CHANGES.rst
Project-URL: PyPI Releases, https://pypi.org/project/pytest-logging-strict
Project-URL: Source code, https://github.com/msftcangoblowm/pytest-logging-strict
Project-URL: Issue tracker, https://github.com/msftcangoblowm/pytest-logging-strict/issues
Project-URL: Mastodon, https://mastodon.social/@msftcangoblowme
Keywords: pytest,strictyaml,yaml,logging.config,caplog
Classifier: Framework :: Pytest
Classifier: Environment :: Console
Classifier: Development Status :: 3 - Alpha
Classifier: Intended Audience :: Developers
Classifier: Operating System :: OS Independent
Classifier: Programming Language :: Python :: 3
Classifier: Programming Language :: Python :: 3.9
Classifier: Programming Language :: Python :: 3.10
Classifier: Programming Language :: Python :: 3.11
Classifier: Programming Language :: Python :: 3.12
Classifier: Programming Language :: Python :: 3.13
Classifier: Programming Language :: Python :: Implementation :: CPython
Classifier: Programming Language :: Python :: Implementation :: PyPy
Classifier: Topic :: System :: Logging
Classifier: Topic :: Software Development :: Testing
Classifier: Natural Language :: English
Classifier: Typing :: Typed
Requires-Python: >=3.9
License-File: LICENSE
License-File: NOTICE.txt
Requires-Dist: logging-strict
Requires-Dist: pytest
Requires-Dist: strictyaml
Requires-Dist: typing-extensions; python_version < "3.11"
Dynamic: license-file
